pythonGraph/__init__.py
pythonGraph/pythonGraph.py
pythonGraph/examples/__init__.py
pythonGraph/examples/animation.py
pythonGraph/examples/drawing.py
pythonGraph/examples/media/alien-spaceship.ogg
pythonGraph/examples/media/magic-wand.ogg
pythonGraph/examples/media/test.png
pythonGraph-0.4.0.dist-info/METADATA
pythonGraph-0.4.0.dist-info/WHEEL
pythonGraph-0.4.0.dist-info/pbr.json
pythonGraph-0.4.0.dist-info/top_level.txt
pythonGraph-0.4.0.dist-info/RECORD
