Metadata-Version: 2.1
Name: pythonGraph
Version: 0.4.0
Summary: simple graphics in Python
Author: Joel Coffman
Author-email: joel.coffman@usafa.edu
License: Unlicense
Classifier: Development Status :: 4 - Beta
Classifier: Programming Language :: Python
Requires-Dist: pbr
Requires-Dist: pygame >=2.0
